gpu_tester/__init__.py
gpu_tester/ddp_worker.py
gpu_tester/main.py
gpu_tester/simple_forward_worker.py
gpu_tester/world_info_from_env.py
gpu_tester-1.2.0.data/data/README.md
gpu_tester-1.2.0.dist-info/LICENSE
gpu_tester-1.2.0.dist-info/METADATA
gpu_tester-1.2.0.dist-info/WHEEL
gpu_tester-1.2.0.dist-info/entry_points.txt
gpu_tester-1.2.0.dist-info/top_level.txt
gpu_tester-1.2.0.dist-info/RECORD
