Metadata-Version: 2.1
Name: gpu-tester
Version: 1.2.0
Summary: A python template
Home-page: https://github.com/rom1504/gpu_tester
Author: Romain Beaumont
Author-email: romain.rom1@gmail.com
License: MIT
Keywords: machine learning
Platform: UNKNOWN
Classifier: Development Status :: 4 - Beta
Classifier: Intended Audience :: Developers
Classifier: Topic :: Scientific/Engineering :: Artificial Intelligence
Classifier: License :: OSI Approved :: MIT License
Classifier: Programming Language :: Python :: 3.6
Requires-Dist: fire
Requires-Dist: numpy
Requires-Dist: torch
